greenjay/__init__.py
greenjay/fileHandler.py
greenjay/logger.py
greenjay/outputConsole.py
greenjay-1.0.1.dist-info/METADATA
greenjay-1.0.1.dist-info/RECORD
greenjay-1.0.1.dist-info/WHEEL
greenjay-1.0.1.dist-info/top_level.txt
