Metadata-Version: 2.1
Name: greenjay
Version: 1.0.1
Summary: Customised Python Logger.
Home-page: UNKNOWN
Author: Jexulie
Author-email: UNKNOWN
License: MIT
Platform: UNKNOWN
Classifier: Development Status :: 5 - Production/Stable
Classifier: Intended Audience :: Developers
Classifier: License :: OSI Approved :: MIT License
Classifier: Programming Language :: Python :: 3
